{"Array":[{"index":0,"name":"흩어진 짐","description":"여행용 짐들이 잔뜩 들어있는 가방이에요."},{"index":1,"name":"칙칙한 큰 수풀","description":"숲으로 가는 길을 막고 있는 커다란 수풀이에요."},{"index":2,"name":"망가진 게시판","description":"페어리들이 소원을 적고는 했던 망가진 게시판이에요."},{"index":3,"name":"망가진 집","description":"어떤 대마법사가 머물렀다는 오두막 집. 망가져 있어요."},{"index":4,"name":"망가진 조리대","description":"페어리들이 사용했던 것 같은 망가진 조리대예요."},{"index":5,"name":"망가진 밭","description":"생기를 잃고 망가진 밭이에요."},{"index":6,"name":"망가진 나무 밭","description":"생기를 잃고 망가진 나무 밭이에요."},{"index":7,"name":"망가진 황금빛 샘","description":"망가진 황금빛 샘이에요."},{"index":8,"name":"망가진 광산","description":"무엇이 잠들어 있을지 모르는 무너진 광산이에요."},{"index":9,"name":"망가진 작업 공방","description":"녹슨 공구가 놓여 있는 망가진 작업 공방이에요."},{"index":10,"name":"누르의 연구소 터","description":"누르가 생활했었던 연구소의 터예요."},{"index":11,"name":"망가진 신전","description":"슬픔이 느껴지는 망가진 신전이에요."},{"index":12,"name":"망가진 던전 입구","description":"봉인이 된 건지, 무너진 건지 모를 망가진 던전 입구예요."},{"index":13,"name":"망가진 세공소","description":"흙먼지에 뒤덮인 망가진 세공소예요."},{"index":14,"name":"망가진 연금솥","description":"오랫동안 방치된 것 같은 망가진 연금솥이에요."},{"index":15,"name":"떠돌이 상인의 자리","description":"대륙 밖에서 날아온 상인이 점찍어둔 자리예요."},{"index":16,"name":"남겨진 시장의 터","description":"망가진 시장의 터에요."},{"index":17,"name":"망가진 다리","description":"망가진 다리예요."},{"index":18,"name":"얼어붙은 마법사","description":"냉기가 뿜어져 나오는 얼음 속에 갇힌 마법사가 있어요."},{"index":19,"name":"큰 수풀","description":"길을 막는 큰 수풀이에요."},{"index":20,"name":"망가진 가구공방","description":"숨겨져 있는 망가진 가구공방이에요."},{"index":21,"name":"망가진 재단소","description":"망가진 재단소예요."},{"index":22,"name":"잠든 미로","description":"잠든 미로예요."},{"index":23,"name":"잠든 넬라","description":"잠든 넬라예요."},{"index":24,"name":"잠든 란스","description":"잠든 란스예요."},{"index":25,"name":"찢어진 페이지","description":"찢어진 페이지입니다."},{"index":26,"name":"누군가의 노트 1","description":"누군가의 노트 1입니다."},{"index":27,"name":"누군가의 노트 2","description":"누군가의 노트 2입니다."},{"index":1000,"name":"일반 상자","description":"나무로 만들어진 상자! 뭘 가지고 있을까요?"},{"index":1001,"name":"푸르스름한 상자","description":"푸르스름한 상자. 무엇 때문에 이런 색이 된 걸까요?"},{"index":1002,"name":"조약돌","description":"작고 귀여운 조약돌. 여러가지 놀이를 할 때에도 쓰여요!"},{"index":1003,"name":"거대한 바위","description":"커다란 돌. 좀 무거워 보이는데…"},{"index":1010,"name":"들풀","description":"작고 귀여운 꽃이 피어 날 초록색 식물이에요."},{"index":1011,"name":"들꽃","description":"작고 귀여운 꽃이에요."},{"index":1013,"name":"나뭇가지","description":"무성했던 숲의 조각인 나뭇가지에요."},{"index":1015,"name":"가문비나무","description":"쑥쑥 자라는 가문비나무."},{"index":2000,"name":"연두색 나무","description":"맑은 하늘과 잘 어울리는 연두색 잎이 피어나요."},{"index":2001,"name":"초록색 나무","description":"초록색 나무예요."},{"index":2002,"name":"작은 연두색 나무","description":"작은 연두색 나무예요."},{"index":2003,"name":"커가는 연두색 나무","description":"쑥쑥 자라는 중인 연두색 나무."},{"index":2004,"name":"가문비나무","description":"쑥쑥 자라는 가문비나무."},{"index":2005,"name":"어린 버드나무","description":"어린 버드나무예요."},{"index":2006,"name":"버드나무","description":"버드나무예요."},{"index":2007,"name":"나뭇가지","description":"무성했던 숲의 조각인 나뭇가지에요."},{"index":2008,"name":"망가진 표지판","description":"망가진 표지판예요."},{"index":2009,"name":"망가진 상자","description":"망가진 상자예요."},{"index":2010,"name":"그루터기","description":"그루터기예요."},{"index":2011,"name":"통나무","description":"쑥쑥 자랐던 나무가 남긴 통나무."},{"index":2012,"name":"그루터기","description":"그루터기예요."},{"index":2013,"name":"들풀","description":"작고 귀여운 꽃이 피어 날 초록색 식물이에요."},{"index":2014,"name":"풀","description":"작고 귀여운 꽃이 피어 날 초록색 식물이에요."},{"index":2015,"name":"수풀","description":"신비로운 향풍기는 수풀이에요."},{"index":2016,"name":"들꽃","description":"작고 귀여운 꽃이에요."},{"index":2017,"name":"돌멩이","description":"커다란 바위에서 떨어져 나온 돌멩이예요."},{"index":2018,"name":"돌덩어리","description":"돌덩어리예요."},{"index":2019,"name":"돌 조각","description":"커다란 바위에서 떨어져 나온 돌멩이예요."},{"index":2020,"name":"돌 부스러기","description":"돌 부스러기예요."},{"index":2021,"name":"고대 석판 조각","description":"고대 석판이에요."},{"index":2022,"name":"작은 고대 돌발판","description":"작은 고대 돌발판이에요."},{"index":2023,"name":"길쭉한 묻힌 바위","description":"길쭉한 묻힌 바위예요."},{"index":2024,"name":"고대 석판","description":"고대 석판이에요."},{"index":2025,"name":"바위","description":"바위예요."},{"index":2026,"name":"길쭉한 묻힌 바위","description":"길쭉한 묻힌 바위예요."},{"index":2027,"name":"신비한 문양바위","description":"신비한 문양바위예요."},{"index":2028,"name":"이끼 자란 돌","description":"이끼가 자란 돌이에요."},{"index":2029,"name":"풍화된 신전 기둥","description":"커다란 바위에서 떨어져 나온 돌멩이예요."},{"index":2030,"name":"망가진 신전 기둥","description":"망가진 신전 기둥이예요"},{"index":2031,"name":"쪼개진 신전 기둥","description":"쪼개진 신전 기둥예요."},{"index":2032,"name":"무너진 폐허","description":"무너진 폐허예요."},{"index":2033,"name":"망가진 돌담","description":"망가진 돌담이에요."},{"index":2034,"name":"오래된 폐허","description":"오래된 폐허예요."},{"index":2035,"name":"잊혀진 폐허","description":"잊혀진 폐허예요."},{"index":2036,"name":"큰 수풀","description":"길을 막는 큰 수풀이에요."},{"index":2100,"name":"잠든 초록색 나무","description":"잠든 초록색 나무예요."},{"index":2101,"name":"잠든 연두색 나무","description":"잠든 연두색 나무예요."},{"index":2102,"name":"마른 나무","description":"마른 나무예요."},{"index":2103,"name":"마른 버드나무","description":"마른 버드나무예요."},{"index":2104,"name":"잠든 어린 버드나무","description":"잠든 어린 버드나무예요."},{"index":2105,"name":"잠든 층나무","description":"잠든 층나무예요."},{"index":2106,"name":"잠든 어린 나무","description":"잠든 어린 나무예요."},{"index":2107,"name":"잠든 가문비나무","description":"잠든 가문비나무예요."},{"index":2108,"name":"가시갈퀴나무","description":"가시갈퀴나무예요."},{"index":2109,"name":"무성한 가시갈퀴나무","description":"무성한 가시갈퀴나무예요."},{"index":2110,"name":"깊게 잠든 가시 수풀","description":"깊게 잠든 가시 수풀예요."},{"index":2111,"name":"작은 가시 덩굴","description":"작은 가시 덩굴예요."},{"index":2112,"name":"마른 기울림 나무","description":"마른 기울림 나무예요."},{"index":2113,"name":"비쩍 마른 가지","description":"비쩍 마른 가지예요."},{"index":2114,"name":"앙상한 마른 가지","description":"앙상한 마른 가지예요."},{"index":2115,"name":"망가진 울타리","description":"망가진 울타리예요."},{"index":2116,"name":"묻힌 상자","description":"묻힌 상자예요."},{"index":2117,"name":"잠든 망가진 상자","description":"잠든 망가진 상자예요."},{"index":2118,"name":"식물이 자란 가시 그루터기","description":"식물이 자란 가시 그루터기예요."},{"index":2119,"name":"깊게 잠든 수풀","description":"깊게 잠든 수풀예요."},{"index":2120,"name":"잠든 들풀","description":"잠든 들풀예요."},{"index":2121,"name":"잠든 풀잎","description":"잠든 풀잎예요."},{"index":2122,"name":"잠든 들꽃","description":"잠든 들꽃예요."},{"index":2123,"name":"잠든 폼폼","description":"잠든 폼폼예요."},{"index":2124,"name":"이끼 낀 바위","description":"이끼 낀 바위예요."},{"index":2125,"name":"잠든 이끼 낀 바위","description":"잠든 이끼 낀 바위예요."},{"index":2126,"name":"바람을 이겨낸 바위","description":"거친 바람에 깎인 바위예요."},{"index":2127,"name":"신전의 주춧돌","description":"신전의 주춧돌예요."},{"index":2128,"name":"조각난 신전 파편","description":"조각난 신전 파편예요."},{"index":2129,"name":"작은 돌 파편","description":"작은 돌 파편예요."},{"index":2130,"name":"무너진 신전 기둥","description":"무너진 신전 기둥예요."},{"index":2131,"name":"풍화되어 잠든 바위","description":"풍화되어 잠든 바위예요."},{"index":2132,"name":"잠든 땅의 각진 돌덩이","description":"잠든 땅의 각진 돌덩이예요."},{"index":2133,"name":"잠든 고대 돌 발판","description":"잠든 고대 돌 발판예요."},{"index":2134,"name":"부서진 돌 파편","description":"부서진 돌 파편예요."},{"index":2135,"name":"무너진 신전 파편","description":"무너진 신전 파편예요."},{"index":2136,"name":"잠든 신전 파편","description":"잠든 신전 파편예요."},{"index":2137,"name":"잠든 신전 기둥","description":"잠든 신전 기둥예요."},{"index":2138,"name":"잠든 신전 그림 조각","description":"잠든 신전 그림 조각예요."},{"index":2139,"name":"무너진 신전 그림 조각","description":"무너진 신전 그림 조각예요."},{"index":2140,"name":"풍화되어 잠든 바위","description":"풍화되어 잠든 바위예요."},{"index":2141,"name":"잠든 땅의 돌맹이","description":"잠든 땅의 돌맹이예요."},{"index":2142,"name":"잠든 보라 이끼 바위","description":"잠든 보라 이끼 바위예요."},{"index":2143,"name":"이빨 바위","description":"이빨 바위예요."},{"index":2144,"name":"가는 이빨 바위","description":"가는 이빨 바위예요."},{"index":2145,"name":"얇은 이빨 바위","description":"얇은 이빨 바위예요."},{"index":2146,"name":"작은 이빨 바위","description":"작은 이빨 바위예요."},{"index":2147,"name":"위험한 이빨 바위","description":"위험한 이빨 바위예요."},{"index":2148,"name":"수상한 늪","description":"수상한 늪예요."},{"index":2149,"name":"음산한 늪","description":"음산한 늪예요."},{"index":3000,"name":"밀기용 바위","description":"힘으로 밀면 밀어지는 바위예요."},{"index":4000,"name":"사과나무 새싹","description":"쑥쑥 자라는 중인 사과나무의 새싹이에요."},{"index":4001,"name":"어린 사과나무","description":"쑥쑥 자라는 중인 어린 사과나무예요."},{"index":4002,"name":"사과나무","description":"붉은 과실을 맺을 사과나무예요."},{"index":4003,"name":"사과나무","description":"붉은 과실이 맺힌 사과나무예요."},{"index":4100,"name":"포도나무 새싹","description":"쑥쑥 자라는 중인 포도나무의 새싹이에요."},{"index":4101,"name":"어린 포도나무","description":"쑥쑥 자라는 중인 어린 포도나무예요."},{"index":4102,"name":"포도나무","description":"보라색 과실을 맺을 포도나무예요."},{"index":4103,"name":"포도나무","description":"보라색 과실이 맺힌 포도나무예요."},{"index":4200,"name":"오렌지나무 새싹","description":"쑥쑥 자라는 중인 오렌지나무의 새싹이에요."},{"index":4201,"name":"어린 오렌지나무","description":"쑥쑥 자라는 중인 어린 오렌지나무예요."},{"index":4202,"name":"오렌지나무","description":"주황색 과실을 맺을 오렌지나무예요."},{"index":4203,"name":"오렌지나무","description":"주황색 과실을 맺은 오렌지나무예요."},{"index":4300,"name":"단풍나무 새싹","description":"쑥쑥 자라는 중인 단풍나무의 새싹이에요."},{"index":4301,"name":"어린 단풍나무","description":"쑥쑥 자라는 중인 어린 단풍나무예요."},{"index":4302,"name":"단풍나무","description":"붉은 잎이 달린 단풍나무예요."},{"index":4303,"name":"단풍나무","description":"진액을 얻을 수 있는 잘 자란 단풍나무예요."},{"index":4400,"name":"복숭아나무 새싹","description":"쑥쑥 자라는 중인 복숭아나무의 새싹이에요."},{"index":4401,"name":"어린 복숭아나무","description":"쑥쑥 자라는 중인 어린 복숭아나무예요."},{"index":4402,"name":"복숭아나무","description":"분홍빛 과실을 맺을 복숭아나무예요."},{"index":4403,"name":"복숭아나무","description":"분홍빛 과실을 맺힌 복숭아나무예요."},{"index":4500,"name":"체리나무 새싹","description":"쑥쑥 자라는 중인 체라나무의 새싹이에요."},{"index":4501,"name":"어린 체리나무","description":"쑥쑥 자라는 중인 어린 체리나무예요."},{"index":4502,"name":"체리나무","description":"작고 붉은 과실을 맺을 체리나무예요."},{"index":4503,"name":"체리나무","description":"작고 붉은 과실을 맺은 체리나무예요."},{"index":10000,"name":"새벽의 숲 초입의 잠든 땅","description":"생기가 남아있는 땅 주변을 감싼 곳이에요."},{"index":10001,"name":"남겨진 잠든 땅","description":"언젠가의 기약이 남겨진 곳이에요."},{"index":10002,"name":"흔적만이 남은 잠든 땅","description":"과거를 되짚었던 흔적이 남은 곳이에요."},{"index":10003,"name":"기적이 내렸던 잠든 땅","description":"따스한 기적이 내렸던 곳이에요."},{"index":10004,"name":"돌이 잠든 땅","description":"페어리가 머물던 커다란 돌이 홀로 남아있어요."},{"index":10005,"name":"거칠어진 잠든 땅","description":"풍요로웠던 곳이지만 지금은 거칠어졌어요."},{"index":10006,"name":"메아리의 잠든 땅","description":"누군가의 목소리가 외롭게 울리고 있어요."},{"index":10007,"name":"환상이 내린 잠든 땅","description":"가만히 걷다 보면 아름다운 환상이 아른거려요."},{"index":10008,"name":"기대가 잠든 땅","description":"새롭게 깨어난다는 기대가 잠든 곳이에요."},{"index":10009,"name":"바람이 잠든 땅","description":"앙상한 가지에 바람이 스치고 있어요."},{"index":10100,"name":"헤매는 잠든 땅","description":"안개가 짙을 때 발을 들이면 길을 헤매게 되는 곳이에요."},{"index":10101,"name":"역사가 잠든 땅","description":"모두가 잊어버린 역사가 잠든 곳이에요."},{"index":10102,"name":"한기가 서린 땅","description":"차가운 기운이 감도는 것 같아요."},{"index":10103,"name":"안개가 스며든 잠든 땅","description":"땅 깊은 곳까지 안개가 스며든 것 같아요."},{"index":10104,"name":"꿈을 꾸는 잠든 땅","description":"이곳에서 잠들면 쉽게 깨어나지 못한다고 해요."},{"index":10105,"name":"시들어가는 잠든 땅","description":"생기 있던 식물이 모두 시들어 버린 곳이에요."},{"index":10106,"name":"고요히 잠든 땅","description":"아무런 소리도 들리지 않는 고요한 곳이에요."},{"index":10107,"name":"잊힌 잠든 땅","description":"무언가 중요한 것이 있었다는 흔적이 있지만 지금은 알 수 없어요."},{"index":10108,"name":"미지의 잠든 땅","description":"아무것도 기록되어 있지 않은 미지의 장소에요."},{"index":10109,"name":"바람 소리 나는 잠든 땅","description":"몸을 울릴 정도로 기묘한 바람 소리가 들리는 곳이에요."},{"index":10200,"name":"비밀스러운 잠든 땅","description":"비밀을 감춘 곳이에요."},{"index":10201,"name":"그늘진 잠든 땅","description":"태양이 보이지 않는 곳이에요."},{"index":10202,"name":"혼란이 얽힌 잠든 땅","description":"방황하던 생물들의 혼란이 얽힌 곳이에요."},{"index":10203,"name":"떠도는 잠든 땅","description":"계속 같은 곳을 맴돌게 돼요."},{"index":10204,"name":"그림자 걸친 잠든 땅","description":"어두운 그림자가 걸쳐있는 곳이에요."},{"index":10205,"name":"기다리는 잠든 땅","description":"찾아올 때까지 이 땅은 기다릴 거예요."},{"index":10206,"name":"비밀을 간직한 잠든 땅","description":"누군가 아무에게도 전하지 않았던 마음이 잠든 곳이에요."},{"index":10207,"name":"수수께끼의 잠든 땅","description":"모두에게 의문이었던 일이 얽혀있던 곳이에요."},{"index":10208,"name":"흐름이 멈춘 잠든 땅","description":"시간의 흐름이 멈춘 것 같은 곳이에요."},{"index":10209,"name":"재앙이 내린 땅","description":"피할 수 없는 재앙이 스친 곳이에요."},{"index":10300,"name":"신실함이 잠든 땅","description":"신을 향한 마음이 푸른 초목과 함께 잠들었어요."},{"index":10301,"name":"햇살이 사라진 잠든 땅","description":"반짝이던 햇살이 더는 보이지 않게 되었어요."},{"index":10302,"name":"꺾인 가지의 잠든 땅","description":"황금빛 가지가 꺾여 사라진 곳이에요."},{"index":10303,"name":"가시덤불의 잠든 땅","description":"뾰족한 가시덤불이 길을 막고 있는 곳이에요."},{"index":10304,"name":"미궁의 잠든 땅","description":"알 수 없는 곳으로 향하게 되는 미궁이 있어요."},{"index":10305,"name":"저주받은 잠든 땅","description":"누가 흘려보냈는지 모를 저주가 깃든 곳이에요."},{"index":10306,"name":"검은 가시의 잠든 땅","description":"새까만 가시가 숨어있는 위험한 곳이에요."},{"index":10307,"name":"별빛이 잠든 땅","description":"별빛도 닿지 않는 깊은 안갯속 숲이에요."},{"index":10308,"name":"검은 깃털의 잠든 땅","description":"까마귀가 우는소리가 들려오는 곳이에요."},{"index":10309,"name":"소중한 것이 잠든 땅","description":"누군가의 소중했던 것이 잠들어버린 곳이에요"},{"index":100000,"name":"얼어붙은 보물상자","description":"얼어붙은 보물상자에요."},{"index":100010,"name":"1챕터 복원 전 다리","description":"1챕터 복원 전 다리에요."},{"index":100020,"name":"한기서린 얼음풀","description":"한기가 서려있는 얼음 풀이예요. 붉은 열매에는 어떤 효능이 있을까요?"},{"index":100030,"name":"오로라 버섯","description":"차가운 눈을 뚫고 자란 버섯. 버섯의 색을 보고 누군가 이름을 붙였어요."},{"index":100100,"name":"열사의 보물상자","description":"열사의 보물상자에요."},{"index":100110,"name":"2챕터 복원 전 다리","description":"2챕터 복원 전 다리에요."},{"index":100120,"name":"작은 사금꽃","description":"사금을 품은 작은 꽃이예요."},{"index":100121,"name":"큰 사금꽃","description":"사금을 품은 큰 꽃이예요."},{"index":100130,"name":"낮은 야자","description":"키가 낮은 야자나무예요. 밑을 지나갈 때 조심해요!"},{"index":100200,"name":"가시덤불 보물상자","description":"가시덤불 보물상자에요."},{"index":100210,"name":"3챕터 복원 전 다리","description":"3챕터 복원 전 다리에요."},{"index":100220,"name":"황금빛 열매","description":"황금빛으로 반짝이는 가시덤불의 열매예요."},{"index":100230,"name":"쌓여 있는 주화","description":"누군가 모아둔 주화가 쌓여 있어요. 주인이 없는 걸까요?"},{"index":28,"name":"망가진 길드 건물","description":"빛바랜 색으로 변해버린 건물이에요."},{"index":10010,"name":"즐거움이 잠든 땅","description":"화목한 웃음소리가 꿈처럼 들려와요."}]}