{"Array": [{"index": 0, "name": "畑", "description": "神の祝福が残っている畑。種をまくと何でも育ちます!"}, {"index": 100, "name": "Lv1 スイート調理台", "description": "少し小さいけれど一通り揃った基本的な調理台。簡単な料理が作れますよ。"}, {"index": 101, "name": "Lv2 スイート調理台", "description": "きちんと整理された調理台。料理の基本は清潔さから始まりますよ。"}, {"index": 102, "name": "Lv3 スイート調理台", "description": "レシピを見ながら一つずつ作っていけば、いつの間にか料理人の道へ進んでいるかも?!"}, {"index": 103, "name": "Lv4 スイート調理台", "description": "より丈夫に補強された調理台。重い食材を置いても問題ありません。"}, {"index": 200, "name": "Lv1 コンコン作業工房", "description": "泥を塗り重ねて作った工房。小さいけれど、思い浮かんだものを作るのに問題ありません。"}, {"index": 201, "name": "Lv2 コンコン作業工房", "description": "レンガを追加して耐久性を強化した工房。以前よりも精巧な道具を作り出すことができます!"}, {"index": 300, "name": "Lv1 スクスク家具工房", "description": "小さな家具を作ることができる工房。周りを飾るものを自分で作ってみましょう！"}, {"index": 400, "name": "Lv1 ブクブク錬金釜", "description": "ブクブクと沸き立つ泡の音が錬金術のときめくする始まりを告げています。"}, {"index": 401, "name": "Lv2 ブクブク錬金釜", "description": "どんな材料でも耐えられるように補強した錬金釜。なんだか甘い匂いがするような気がするけど?!"}, {"index": 402, "name": "Lv3 ブクブク錬金釜", "description": "煙がもくもくと立ち上る錬金釜。ちゃんと作られている証拠でしょうか…?"}, {"index": 800, "name": "Lv1 黄金色の泉", "description": "ゴールドが溢れ出る神秘な泉です。"}, {"index": 801, "name": "Lv2 黄金色の泉", "description": "ゴールドが溢れ出る神秘な泉です。"}, {"index": 802, "name": "Lv3 黄金色の泉", "description": "ゴールドが溢れ出る神秘な泉です。"}, {"index": 803, "name": "Lv4 黄金色の泉", "description": "ゴールドが溢れ出る神秘な泉です。"}, {"index": 900, "name": "眠ってしまった夢の神殿", "description": "光明ですら入らない森と茨の間で長い間眠っていたとある夢。"}, {"index": 901, "name": "覚めてくる夢の神殿", "description": "長い間止まっていた時間がゆっくりと目を覚まし、昇ってくる光を見つめています。"}, {"index": 902, "name": "色褪せた記憶の神殿", "description": "過去の祝福が色褪せていても、その時の光はまだ希望を抱いています。"}, {"index": 903, "name": "希望を囁く神殿", "description": "完全に覚めた時間が長い間深く沈んでいた希望を歌っています。"}, {"index": 1000, "name": "木の畑", "description": "木を植えることができる肥沃な畑です。"}, {"index": 1100, "name": "Lv1 鉱山", "description": "はじまりが事の半分というから、ホーを手にすればもう半分成ったことになるでしょう？"}, {"index": 1101, "name": "Lv2 鉱山", "description": "もっと多様なものを作りたいときに活用できる鉱脈が隠されている鉱山！"}, {"index": 1500, "name": "壊れた小屋", "description": "時間につれ壊れてしまった小屋です。"}, {"index": 1501, "name": "魔法使いの家", "description": "偉大な魔法使いが住んでいた小屋。神殿を見る方向に建てられました。"}, {"index": 1600, "name": "Lv1 博物館", "description": -1}, {"index": 1601, "name": "Lv1 博物館", "description": -1}, {"index": 1602, "name": "Lv1 博物館", "description": -1}, {"index": 1603, "name": "Lv1 博物館", "description": -1}, {"index": 1700, "name": "ヌル研究所", "description": "ヌルが設立した研究所。遺物に関連するものを研究し、復元することができます！"}, {"index": 1800, "name": "放浪商人", "description": "怪しげな見た目の流れ商人の店。まさに世界中の全ての品が集まっているようです。"}, {"index": 1900, "name": "願い掲示板", "description": "いつも助けてくれる妖精たちのための掲示板です！何か手伝うことはできるでしょうか？"}, {"index": 2000, "name": "ダンジョン入口", "description": "他の場所へと繋がる未知の入口。ここから先はどこに繋がっているのでしょうか？"}, {"index": 2100, "name": "小さなギルド", "description": "小ぢんまりと集まってギルド活動ができる建物です。"}, {"index": 2101, "name": "団らんのギルド", "description": "みんなで楽しくギルド活動ができる建物です。"}, {"index": 2102, "name": "活気のあるギルド", "description": "本格的なギルド活動資格を得た証！これからもっと多くのことを一緒にやりましょう！"}, {"index": 104, "name": "Lv5 スイート調理台", "description": "料理の始まりは材料を整えることから！ 整えたものをきちんと整理すれば、混乱することはないでしょう。"}, {"index": 403, "name": "Lv4 ブクブク錬金釜", "description": "これでは足りない！もっと多くのポーションを作り出すために改造した錬金術の釜です。"}, {"index": 500, "name": "Lv1 ぽかぽか仕立て屋", "description": "様々な布や服を作ることができる仕立て屋です。"}, {"index": 501, "name": "Lv2 ぽかぽか仕立て屋", "description": "様々な布や服を作ることができる仕立て屋です。"}, {"index": 502, "name": "Lv3 ぽかぽか仕立て屋", "description": "様々な布や服を作ることができる仕立て屋です。"}, {"index": 503, "name": "Lv4 ぽかぽか仕立て屋", "description": "様々な布や服を作ることができる仕立て屋です。"}, {"index": 600, "name": "Lv1 キラキラ工房", "description": "古びたテーブルの上に置かれた一つののみで偉大な職人になれるなんて信じられません！"}, {"index": 601, "name": "Lv2 キラキラ工房", "description": "めちゃくちゃな練習を続けていますが、今では工芸の基本を熟練してできるようになりました。"}, {"index": 602, "name": "Lv3 キラキラ工房", "description": "強化されたテーブルの上に散らばった材料。継続的な練習だけが技術を向上させます。"}, {"index": 603, "name": "Lv4 キラキラ工房", "description": "職人への道の始まりは周りをきれいに片付けることから始まります。"}, {"index": 804, "name": "Lv5 黄金色の泉", "description": "ゴールドが溢れ出る神秘な泉です。"}, {"index": 904, "name": "奇跡が咲き誇る神殿。", "description": "星々の歌が奇跡を育み、進むべき方向を照らしています。"}, {"index": 1102, "name": "Lv3 鉱山", "description": "何よりも最も重要なのは皆の安全です！そして実用性のために鉱山にレールを敷きました。"}, {"index": 1604, "name": "Lv5 博物館", "description": -1}]}