{"Array":[{"index":0,"displayType":0,"consumeType":-1,"consumeCode":-1,"consumeValue":-1,"finishCost":0,"ink":-1,"gold":0,"x":-110,"y":196,"xSize":-1,"ySize":-1},{"index":1,"displayType":0,"consumeType":-1,"consumeCode":-1,"consumeValue":-1,"finishCost":0,"ink":-1,"gold":0,"x":-111,"y":207,"xSize":-1,"ySize":-1},{"index":2,"displayType":0,"consumeType":-1,"consumeCode":-1,"consumeValue":-1,"finishCost":0,"ink":-1,"gold":0,"x":-99,"y":195,"xSize":-1,"ySize":-1},{"index":3,"displayType":0,"consumeType":-1,"consumeCode":-1,"consumeValue":-1,"finishCost":0,"ink":-1,"gold":0,"x":-111,"y":222,"xSize":-1,"ySize":-1},{"index":4,"displayType":0,"consumeType":-1,"consumeCode":-1,"consumeValue":-1,"finishCost":0,"ink":-1,"gold":0,"x":-84,"y":195,"xSize":-1,"ySize":-1},{"index":5,"displayType":0,"consumeType":-1,"consumeCode":-1,"consumeValue":-1,"finishCost":0,"ink":-1,"gold":0,"x":-99,"y":225,"xSize":-1,"ySize":-1},{"index":6,"displayType":0,"consumeType":-1,"consumeCode":-1,"consumeValue":-1,"finishCost":0,"ink":-1,"gold":0,"x":-81,"y":207,"xSize":-1,"ySize":-1},{"index":100,"displayType":0,"consumeType":-1,"consumeCode":-1,"consumeValue":-1,"finishCost":0,"ink":-1,"gold":0,"x":-22,"y":69,"xSize":-1,"ySize":-1},{"index":101,"displayType":0,"consumeType":-1,"consumeCode":-1,"consumeValue":-1,"finishCost":0,"ink":-1,"gold":0,"x":-15,"y":62,"xSize":-1,"ySize":-1},{"index":102,"displayType":0,"consumeType":-1,"consumeCode":-1,"consumeValue":-1,"finishCost":0,"ink":-1,"gold":0,"x":-21,"y":87,"xSize":-1,"ySize":-1},{"index":103,"displayType":0,"consumeType":-1,"consumeCode":-1,"consumeValue":-1,"finishCost":0,"ink":-1,"gold":0,"x":3,"y":63,"xSize":-1,"ySize":-1},{"index":104,"displayType":0,"consumeType":-1,"consumeCode":-1,"consumeValue":-1,"finishCost":0,"ink":-1,"gold":0,"x":-13,"y":87,"xSize":-1,"ySize":-1},{"index":105,"displayType":0,"consumeType":-1,"consumeCode":-1,"consumeValue":-1,"finishCost":0,"ink":-1,"gold":0,"x":3,"y":71,"xSize":-1,"ySize":-1},{"index":106,"displayType":0,"consumeType":-1,"consumeCode":-1,"consumeValue":-1,"finishCost":0,"ink":-1,"gold":0,"x":-5,"y":87,"xSize":-1,"ySize":-1},{"index":107,"displayType":0,"consumeType":-1,"consumeCode":-1,"consumeValue":-1,"finishCost":0,"ink":-1,"gold":0,"x":3,"y":79,"xSize":-1,"ySize":-1},{"index":108,"displayType":0,"consumeType":-1,"consumeCode":-1,"consumeValue":-1,"finishCost":0,"ink":-1,"gold":0,"x":3,"y":87,"xSize":-1,"ySize":-1},{"index":109,"displayType":1,"consumeType":-1,"consumeCode":-1,"consumeValue":-1,"finishCost":0,"ink":-1,"gold":0,"x":-22,"y":97,"xSize":5,"ySize":10},{"index":110,"displayType":1,"consumeType":-1,"consumeCode":-1,"consumeValue":-1,"finishCost":0,"ink":-1,"gold":0,"x":-14,"y":97,"xSize":9,"ySize":10},{"index":111,"displayType":1,"consumeType":-1,"consumeCode":-1,"consumeValue":-1,"finishCost":0,"ink":-1,"gold":0,"x":-4,"y":97,"xSize":9,"ySize":10},{"index":112,"displayType":1,"consumeType":-1,"consumeCode":-1,"consumeValue":-1,"finishCost":0,"ink":-1,"gold":0,"x":8,"y":97,"xSize":5,"ySize":10},{"index":113,"displayType":1,"consumeType":-1,"consumeCode":-1,"consumeValue":-1,"finishCost":0,"ink":-1,"gold":0,"x":13,"y":96,"xSize":5,"ySize":10},{"index":114,"displayType":1,"consumeType":-1,"consumeCode":-1,"consumeValue":-1,"finishCost":0,"ink":-1,"gold":0,"x":13,"y":88,"xSize":9,"ySize":10},{"index":115,"displayType":1,"consumeType":-1,"consumeCode":-1,"consumeValue":-1,"finishCost":0,"ink":-1,"gold":0,"x":13,"y":78,"xSize":9,"ySize":10},{"index":116,"displayType":1,"consumeType":-1,"consumeCode":-1,"consumeValue":-1,"finishCost":0,"ink":-1,"gold":0,"x":13,"y":66,"xSize":5,"ySize":10},{"index":200,"displayType":0,"consumeType":4,"consumeCode":204,"consumeValue":50,"finishCost":500,"ink":20,"gold":500000,"x":49,"y":1,"xSize":-1,"ySize":-1},{"index":201,"displayType":0,"consumeType":4,"consumeCode":108,"consumeValue":50,"finishCost":1000,"ink":20,"gold":1000000,"x":59,"y":-6,"xSize":-1,"ySize":-1},{"index":202,"displayType":0,"consumeType":4,"consumeCode":206,"consumeValue":50,"finishCost":1500,"ink":20,"gold":1500000,"x":49,"y":17,"xSize":-1,"ySize":-1},{"index":203,"displayType":0,"consumeType":4,"consumeCode":300,"consumeValue":50,"finishCost":2000,"ink":25,"gold":2000000,"x":68,"y":-6,"xSize":-1,"ySize":-1},{"index":204,"displayType":0,"consumeType":4,"consumeCode":111,"consumeValue":50,"finishCost":2500,"ink":25,"gold":2500000,"x":59,"y":22,"xSize":-1,"ySize":-1},{"index":205,"displayType":0,"consumeType":4,"consumeCode":400,"consumeValue":50,"finishCost":3000,"ink":25,"gold":3000000,"x":77,"y":5,"xSize":-1,"ySize":-1},{"index":206,"displayType":0,"consumeType":4,"consumeCode":112,"consumeValue":50,"finishCost":3500,"ink":30,"gold":3500000,"x":68,"y":22,"xSize":-1,"ySize":-1},{"index":207,"displayType":0,"consumeType":4,"consumeCode":303,"consumeValue":50,"finishCost":4000,"ink":30,"gold":4000000,"x":77,"y":14,"xSize":-1,"ySize":-1},{"index":208,"displayType":1,"consumeType":4,"consumeCode":205,"consumeValue":50,"finishCost":500,"ink":20,"gold":500000,"x":47,"y":28,"xSize":5,"ySize":10},{"index":209,"displayType":1,"consumeType":4,"consumeCode":109,"consumeValue":50,"finishCost":1000,"ink":20,"gold":1000000,"x":55,"y":28,"xSize":9,"ySize":10},{"index":210,"displayType":1,"consumeType":4,"consumeCode":207,"consumeValue":50,"finishCost":1500,"ink":20,"gold":1500000,"x":65,"y":28,"xSize":9,"ySize":10},{"index":211,"displayType":1,"consumeType":4,"consumeCode":301,"consumeValue":50,"finishCost":2000,"ink":25,"gold":2000000,"x":77,"y":28,"xSize":5,"ySize":10},{"index":212,"displayType":1,"consumeType":4,"consumeCode":208,"consumeValue":50,"finishCost":2500,"ink":25,"gold":2500000,"x":82,"y":27,"xSize":5,"ySize":10},{"index":213,"displayType":1,"consumeType":4,"consumeCode":302,"consumeValue":50,"finishCost":3000,"ink":25,"gold":3000000,"x":82,"y":19,"xSize":9,"ySize":10},{"index":214,"displayType":1,"consumeType":4,"consumeCode":401,"consumeValue":50,"finishCost":3500,"ink":30,"gold":3500000,"x":82,"y":9,"xSize":9,"ySize":10},{"index":215,"displayType":1,"consumeType":4,"consumeCode":209,"consumeValue":50,"finishCost":4000,"ink":30,"gold":4000000,"x":82,"y":-3,"xSize":5,"ySize":10},{"index":300,"displayType":0,"consumeType":4,"consumeCode":113,"consumeValue":100,"finishCost":5000,"ink":35,"gold":5000000,"x":118,"y":-67,"xSize":-1,"ySize":-1},{"index":301,"displayType":0,"consumeType":4,"consumeCode":500,"consumeValue":100,"finishCost":7500,"ink":35,"gold":7500000,"x":125,"y":-74,"xSize":-1,"ySize":-1},{"index":302,"displayType":0,"consumeType":4,"consumeCode":114,"consumeValue":100,"finishCost":10000,"ink":40,"gold":10000000,"x":120,"y":-48,"xSize":-1,"ySize":-1},{"index":303,"displayType":0,"consumeType":4,"consumeCode":115,"consumeValue":100,"finishCost":12500,"ink":40,"gold":12500000,"x":144,"y":-72,"xSize":-1,"ySize":-1},{"index":304,"displayType":0,"consumeType":4,"consumeCode":306,"consumeValue":100,"finishCost":15000,"ink":45,"gold":15000000,"x":132,"y":-48,"xSize":-1,"ySize":-1},{"index":305,"displayType":0,"consumeType":4,"consumeCode":211,"consumeValue":100,"finishCost":17500,"ink":45,"gold":17500000,"x":144,"y":-60,"xSize":-1,"ySize":-1},{"index":306,"displayType":0,"consumeType":4,"consumeCode":117,"consumeValue":100,"finishCost":20000,"ink":50,"gold":20000000,"x":144,"y":-48,"xSize":-1,"ySize":-1},{"index":307,"displayType":0,"consumeType":4,"consumeCode":308,"consumeValue":100,"finishCost":25000,"ink":50,"gold":25000000,"x":132,"y":-60,"xSize":-1,"ySize":-1},{"index":308,"displayType":1,"consumeType":4,"consumeCode":304,"consumeValue":100,"finishCost":5000,"ink":35,"gold":5000000,"x":116,"y":-41,"xSize":5,"ySize":10},{"index":309,"displayType":1,"consumeType":4,"consumeCode":210,"consumeValue":100,"finishCost":7500,"ink":35,"gold":7500000,"x":124,"y":-41,"xSize":9,"ySize":10},{"index":310,"displayType":1,"consumeType":4,"consumeCode":305,"consumeValue":100,"finishCost":10000,"ink":40,"gold":10000000,"x":134,"y":-41,"xSize":9,"ySize":10},{"index":311,"displayType":1,"consumeType":4,"consumeCode":501,"consumeValue":100,"finishCost":12500,"ink":40,"gold":12500000,"x":146,"y":-41,"xSize":5,"ySize":10},{"index":312,"displayType":1,"consumeType":4,"consumeCode":116,"consumeValue":100,"finishCost":15000,"ink":45,"gold":15000000,"x":151,"y":-42,"xSize":5,"ySize":10},{"index":313,"displayType":1,"consumeType":4,"consumeCode":307,"consumeValue":100,"finishCost":17500,"ink":45,"gold":17500000,"x":151,"y":-50,"xSize":9,"ySize":10},{"index":314,"displayType":1,"consumeType":4,"consumeCode":502,"consumeValue":100,"finishCost":20000,"ink":50,"gold":20000000,"x":151,"y":-60,"xSize":9,"ySize":10},{"index":315,"displayType":1,"consumeType":4,"consumeCode":212,"consumeValue":100,"finishCost":25000,"ink":50,"gold":25000000,"x":151,"y":-72,"xSize":5,"ySize":10},{"index":400,"displayType":0,"consumeType":4,"consumeCode":113,"consumeValue":100,"finishCost":25000,"ink":50,"gold":25000000,"x":189,"y":-118,"xSize":-1,"ySize":-1},{"index":401,"displayType":0,"consumeType":4,"consumeCode":500,"consumeValue":100,"finishCost":27500,"ink":55,"gold":27500000,"x":192,"y":-129,"xSize":-1,"ySize":-1},{"index":402,"displayType":0,"consumeType":4,"consumeCode":114,"consumeValue":100,"finishCost":30000,"ink":60,"gold":30000000,"x":189,"y":-141,"xSize":-1,"ySize":-1},{"index":403,"displayType":0,"consumeType":4,"consumeCode":115,"consumeValue":100,"finishCost":32500,"ink":65,"gold":32500000,"x":201,"y":-120,"xSize":-1,"ySize":-1},{"index":404,"displayType":0,"consumeType":4,"consumeCode":306,"consumeValue":100,"finishCost":35000,"ink":70,"gold":35000000,"x":201,"y":-138,"xSize":-1,"ySize":-1},{"index":405,"displayType":0,"consumeType":4,"consumeCode":211,"consumeValue":100,"finishCost":37500,"ink":75,"gold":37500000,"x":212,"y":-118,"xSize":-1,"ySize":-1},{"index":406,"displayType":0,"consumeType":4,"consumeCode":117,"consumeValue":100,"finishCost":40000,"ink":80,"gold":40000000,"x":210,"y":-129,"xSize":-1,"ySize":-1},{"index":407,"displayType":0,"consumeType":4,"consumeCode":308,"consumeValue":100,"finishCost":45000,"ink":90,"gold":45000000,"x":212,"y":-141,"xSize":-1,"ySize":-1},{"index":408,"displayType":1,"consumeType":4,"consumeCode":304,"consumeValue":100,"finishCost":25000,"ink":50,"gold":25000000,"x":198,"y":-101,"xSize":5,"ySize":10},{"index":409,"displayType":1,"consumeType":4,"consumeCode":210,"consumeValue":100,"finishCost":27500,"ink":55,"gold":27500000,"x":210,"y":-101,"xSize":9,"ySize":10},{"index":410,"displayType":1,"consumeType":4,"consumeCode":305,"consumeValue":100,"finishCost":30000,"ink":60,"gold":30000000,"x":220,"y":-101,"xSize":9,"ySize":10},{"index":411,"displayType":1,"consumeType":4,"consumeCode":501,"consumeValue":100,"finishCost":32500,"ink":65,"gold":32500000,"x":228,"y":-101,"xSize":5,"ySize":10},{"index":412,"displayType":1,"consumeType":4,"consumeCode":116,"consumeValue":100,"finishCost":35000,"ink":70,"gold":35000000,"x":229,"y":-102,"xSize":5,"ySize":10},{"index":413,"displayType":1,"consumeType":4,"consumeCode":307,"consumeValue":100,"finishCost":37500,"ink":75,"gold":37500000,"x":229,"y":-110,"xSize":9,"ySize":10},{"index":414,"displayType":1,"consumeType":4,"consumeCode":502,"consumeValue":100,"finishCost":40000,"ink":80,"gold":40000000,"x":229,"y":-120,"xSize":9,"ySize":10},{"index":415,"displayType":1,"consumeType":4,"consumeCode":212,"consumeValue":100,"finishCost":45000,"ink":90,"gold":45000000,"x":229,"y":-132,"xSize":5,"ySize":10}]}