{"Array":[{"index":0,"openType":-1,"openCode":-1,"openValue":-1,"missionType":58,"requestType":-1,"requestCode":-1,"requestValue":8,"rewardType":1,"rewardCode":-1,"rewardValue":30,"knowledge":-1,"rewardGuildCoin":-1,"rewardGuildExp":-1},{"index":1,"openType":0,"openCode":-1,"openValue":1,"missionType":60,"requestType":-1,"requestCode":-1,"requestValue":1,"rewardType":1,"rewardCode":-1,"rewardValue":3,"knowledge":-1,"rewardGuildCoin":-1,"rewardGuildExp":-1},{"index":2,"openType":1,"openCode":-1,"openValue":93,"missionType":11,"requestType":-1,"requestCode":-1,"requestValue":3,"rewardType":12,"rewardCode":-1,"rewardValue":20,"knowledge":-1,"rewardGuildCoin":-1,"rewardGuildExp":-1},{"index":3,"openType":0,"openCode":-1,"openValue":1,"missionType":20,"requestType":-1,"requestCode":-1,"requestValue":20,"rewardType":0,"rewardCode":-1,"rewardValue":1000,"knowledge":-1,"rewardGuildCoin":-1,"rewardGuildExp":-1},{"index":4,"openType":0,"openCode":-1,"openValue":1,"missionType":18,"requestType":-1,"requestCode":-1,"requestValue":5,"rewardType":12,"rewardCode":-1,"rewardValue":20,"knowledge":-1,"rewardGuildCoin":-1,"rewardGuildExp":-1},{"index":5,"openType":0,"openCode":-1,"openValue":1,"missionType":16,"requestType":-1,"requestCode":-1,"requestValue":10,"rewardType":0,"rewardCode":-1,"rewardValue":1000,"knowledge":-1,"rewardGuildCoin":-1,"rewardGuildExp":-1},{"index":6,"openType":0,"openCode":-1,"openValue":1,"missionType":15,"requestType":-1,"requestCode":-1,"requestValue":3,"rewardType":12,"rewardCode":-1,"rewardValue":20,"knowledge":-1,"rewardGuildCoin":-1,"rewardGuildExp":-1},{"index":7,"openType":0,"openCode":-1,"openValue":1,"missionType":4,"requestType":-1,"requestCode":-1,"requestValue":10,"rewardType":0,"rewardCode":-1,"rewardValue":1000,"knowledge":-1,"rewardGuildCoin":-1,"rewardGuildExp":-1},{"index":8,"openType":0,"openCode":-1,"openValue":11,"missionType":1,"requestType":102,"requestCode":-1,"requestValue":5,"rewardType":0,"rewardCode":-1,"rewardValue":1000,"knowledge":-1,"rewardGuildCoin":-1,"rewardGuildExp":-1},{"index":9,"openType":0,"openCode":-1,"openValue":1,"missionType":8,"requestType":15,"requestCode":1000,"requestValue":10,"rewardType":4,"rewardCode":0,"rewardValue":5,"knowledge":-1,"rewardGuildCoin":-1,"rewardGuildExp":-1},{"index":10,"openType":0,"openCode":-1,"openValue":9,"missionType":8,"requestType":15,"requestCode":1001,"requestValue":10,"rewardType":4,"rewardCode":1,"rewardValue":5,"knowledge":-1,"rewardGuildCoin":-1,"rewardGuildExp":-1},{"index":11,"openType":0,"openCode":-1,"openValue":13,"missionType":8,"requestType":15,"requestCode":1002,"requestValue":10,"rewardType":4,"rewardCode":2,"rewardValue":5,"knowledge":-1,"rewardGuildCoin":-1,"rewardGuildExp":-1},{"index":12,"openType":0,"openCode":-1,"openValue":22,"missionType":8,"requestType":15,"requestCode":1003,"requestValue":10,"rewardType":0,"rewardCode":-1,"rewardValue":1000,"knowledge":-1,"rewardGuildCoin":-1,"rewardGuildExp":-1},{"index":13,"openType":0,"openCode":-1,"openValue":31,"missionType":8,"requestType":15,"requestCode":1004,"requestValue":10,"rewardType":0,"rewardCode":-1,"rewardValue":1000,"knowledge":-1,"rewardGuildCoin":-1,"rewardGuildExp":-1},{"index":14,"openType":0,"openCode":-1,"openValue":40,"missionType":8,"requestType":15,"requestCode":1005,"requestValue":10,"rewardType":0,"rewardCode":-1,"rewardValue":1000,"knowledge":-1,"rewardGuildCoin":-1,"rewardGuildExp":-1},{"index":15,"openType":0,"openCode":-1,"openValue":1,"missionType":8,"requestType":15,"requestCode":2000,"requestValue":10,"rewardType":4,"rewardCode":3,"rewardValue":5,"knowledge":-1,"rewardGuildCoin":-1,"rewardGuildExp":-1},{"index":16,"openType":0,"openCode":-1,"openValue":1,"missionType":8,"requestType":15,"requestCode":2001,"requestValue":10,"rewardType":4,"rewardCode":4,"rewardValue":5,"knowledge":-1,"rewardGuildCoin":-1,"rewardGuildExp":-1},{"index":17,"openType":0,"openCode":-1,"openValue":8,"missionType":8,"requestType":15,"requestCode":2002,"requestValue":10,"rewardType":0,"rewardCode":-1,"rewardValue":1000,"knowledge":-1,"rewardGuildCoin":-1,"rewardGuildExp":-1},{"index":18,"openType":0,"openCode":-1,"openValue":12,"missionType":8,"requestType":15,"requestCode":2003,"requestValue":10,"rewardType":0,"rewardCode":-1,"rewardValue":1000,"knowledge":-1,"rewardGuildCoin":-1,"rewardGuildExp":-1},{"index":19,"openType":0,"openCode":-1,"openValue":20,"missionType":8,"requestType":15,"requestCode":2004,"requestValue":10,"rewardType":0,"rewardCode":-1,"rewardValue":1000,"knowledge":-1,"rewardGuildCoin":-1,"rewardGuildExp":-1},{"index":20,"openType":0,"openCode":-1,"openValue":28,"missionType":8,"requestType":15,"requestCode":2005,"requestValue":10,"rewardType":0,"rewardCode":-1,"rewardValue":1000,"knowledge":-1,"rewardGuildCoin":-1,"rewardGuildExp":-1},{"index":21,"openType":0,"openCode":-1,"openValue":33,"missionType":8,"requestType":15,"requestCode":2006,"requestValue":10,"rewardType":0,"rewardCode":-1,"rewardValue":1000,"knowledge":-1,"rewardGuildCoin":-1,"rewardGuildExp":-1},{"index":22,"openType":0,"openCode":-1,"openValue":43,"missionType":8,"requestType":15,"requestCode":2007,"requestValue":10,"rewardType":0,"rewardCode":-1,"rewardValue":1000,"knowledge":-1,"rewardGuildCoin":-1,"rewardGuildExp":-1},{"index":100,"openType":-1,"openCode":-1,"openValue":-1,"missionType":59,"requestType":-1,"requestCode":-1,"requestValue":8,"rewardType":25,"rewardCode":-1,"rewardValue":1,"knowledge":-1,"rewardGuildCoin":-1,"rewardGuildExp":-1},{"index":101,"openType":0,"openCode":-1,"openValue":1,"missionType":60,"requestType":-1,"requestCode":-1,"requestValue":5,"rewardType":1,"rewardCode":-1,"rewardValue":30,"knowledge":-1,"rewardGuildCoin":-1,"rewardGuildExp":-1},{"index":102,"openType":0,"openCode":-1,"openValue":1,"missionType":58,"requestType":-1,"requestCode":-1,"requestValue":30,"rewardType":19,"rewardCode":-1,"rewardValue":3,"knowledge":-1,"rewardGuildCoin":-1,"rewardGuildExp":-1},{"index":103,"openType":0,"openCode":-1,"openValue":1,"missionType":20,"requestType":-1,"requestCode":-1,"requestValue":300,"rewardType":1,"rewardCode":-1,"rewardValue":30,"knowledge":-1,"rewardGuildCoin":-1,"rewardGuildExp":-1},{"index":104,"openType":0,"openCode":-1,"openValue":1,"missionType":18,"requestType":-1,"requestCode":-1,"requestValue":100,"rewardType":19,"rewardCode":-1,"rewardValue":3,"knowledge":-1,"rewardGuildCoin":-1,"rewardGuildExp":-1},{"index":105,"openType":0,"openCode":-1,"openValue":1,"missionType":16,"requestType":-1,"requestCode":-1,"requestValue":300,"rewardType":1,"rewardCode":-1,"rewardValue":30,"knowledge":-1,"rewardGuildCoin":-1,"rewardGuildExp":-1},{"index":106,"openType":0,"openCode":-1,"openValue":1,"missionType":15,"requestType":-1,"requestCode":-1,"requestValue":30,"rewardType":19,"rewardCode":-1,"rewardValue":3,"knowledge":-1,"rewardGuildCoin":-1,"rewardGuildExp":-1},{"index":107,"openType":0,"openCode":-1,"openValue":1,"missionType":4,"requestType":-1,"requestCode":-1,"requestValue":200,"rewardType":1,"rewardCode":-1,"rewardValue":30,"knowledge":-1,"rewardGuildCoin":-1,"rewardGuildExp":-1},{"index":108,"openType":0,"openCode":-1,"openValue":1,"missionType":1,"requestType":102,"requestCode":-1,"requestValue":100,"rewardType":1,"rewardCode":-1,"rewardValue":30,"knowledge":-1,"rewardGuildCoin":-1,"rewardGuildExp":-1},{"index":200,"openType":0,"openCode":-1,"openValue":1,"missionType":60,"requestType":-1,"requestCode":-1,"requestValue":1,"rewardType":29,"rewardCode":-1,"rewardValue":500,"knowledge":-1,"rewardGuildCoin":-1,"rewardGuildExp":250},{"index":201,"openType":1,"openCode":-1,"openValue":236,"missionType":11,"requestType":-1,"requestCode":-1,"requestValue":3,"rewardType":29,"rewardCode":-1,"rewardValue":500,"knowledge":-1,"rewardGuildCoin":-1,"rewardGuildExp":250},{"index":202,"openType":0,"openCode":-1,"openValue":1,"missionType":20,"requestType":-1,"requestCode":-1,"requestValue":20,"rewardType":29,"rewardCode":-1,"rewardValue":500,"knowledge":-1,"rewardGuildCoin":-1,"rewardGuildExp":250},{"index":203,"openType":0,"openCode":-1,"openValue":1,"missionType":18,"requestType":-1,"requestCode":-1,"requestValue":10,"rewardType":29,"rewardCode":-1,"rewardValue":500,"knowledge":-1,"rewardGuildCoin":-1,"rewardGuildExp":250},{"index":204,"openType":0,"openCode":-1,"openValue":1,"missionType":16,"requestType":-1,"requestCode":-1,"requestValue":10,"rewardType":29,"rewardCode":-1,"rewardValue":500,"knowledge":-1,"rewardGuildCoin":-1,"rewardGuildExp":250},{"index":205,"openType":0,"openCode":-1,"openValue":1,"missionType":15,"requestType":-1,"requestCode":-1,"requestValue":5,"rewardType":29,"rewardCode":-1,"rewardValue":500,"knowledge":-1,"rewardGuildCoin":-1,"rewardGuildExp":250},{"index":206,"openType":0,"openCode":-1,"openValue":1,"missionType":4,"requestType":-1,"requestCode":-1,"requestValue":20,"rewardType":29,"rewardCode":-1,"rewardValue":500,"knowledge":-1,"rewardGuildCoin":-1,"rewardGuildExp":250},{"index":207,"openType":0,"openCode":-1,"openValue":11,"missionType":1,"requestType":102,"requestCode":-1,"requestValue":5,"rewardType":29,"rewardCode":-1,"rewardValue":500,"knowledge":-1,"rewardGuildCoin":-1,"rewardGuildExp":250},{"index":208,"openType":0,"openCode":-1,"openValue":1,"missionType":8,"requestType":15,"requestCode":-1,"requestValue":30,"rewardType":29,"rewardCode":-1,"rewardValue":500,"knowledge":-1,"rewardGuildCoin":-1,"rewardGuildExp":250},{"index":1000,"openType":0,"openCode":-1,"openValue":1,"missionType":1,"requestType":102,"requestCode":-1,"requestValue":10,"rewardType":1,"rewardCode":-1,"rewardValue":5,"knowledge":3,"rewardGuildCoin":10,"rewardGuildExp":5},{"index":1001,"openType":0,"openCode":-1,"openValue":1,"missionType":1,"requestType":102,"requestCode":-1,"requestValue":100,"rewardType":1,"rewardCode":-1,"rewardValue":10,"knowledge":5,"rewardGuildCoin":10,"rewardGuildExp":5},{"index":1002,"openType":0,"openCode":-1,"openValue":1,"missionType":1,"requestType":102,"requestCode":-1,"requestValue":500,"rewardType":1,"rewardCode":-1,"rewardValue":20,"knowledge":10,"rewardGuildCoin":10,"rewardGuildExp":5},{"index":1003,"openType":0,"openCode":-1,"openValue":1,"missionType":1,"requestType":102,"requestCode":-1,"requestValue":1000,"rewardType":1,"rewardCode":-1,"rewardValue":30,"knowledge":15,"rewardGuildCoin":10,"rewardGuildExp":5},{"index":1004,"openType":0,"openCode":-1,"openValue":1,"missionType":1,"requestType":102,"requestCode":-1,"requestValue":5000,"rewardType":1,"rewardCode":-1,"rewardValue":50,"knowledge":20,"rewardGuildCoin":10,"rewardGuildExp":5},{"index":1005,"openType":0,"openCode":-1,"openValue":1,"missionType":1,"requestType":102,"requestCode":-1,"requestValue":10000,"rewardType":1,"rewardCode":-1,"rewardValue":100,"knowledge":30,"rewardGuildCoin":10,"rewardGuildExp":5},{"index":2000,"openType":0,"openCode":-1,"openValue":1,"missionType":2,"requestType":-1,"requestCode":-1,"requestValue":3,"rewardType":1,"rewardCode":-1,"rewardValue":5,"knowledge":3,"rewardGuildCoin":10,"rewardGuildExp":5},{"index":2001,"openType":0,"openCode":-1,"openValue":1,"missionType":2,"requestType":-1,"requestCode":-1,"requestValue":30,"rewardType":1,"rewardCode":-1,"rewardValue":10,"knowledge":5,"rewardGuildCoin":10,"rewardGuildExp":5},{"index":2002,"openType":0,"openCode":-1,"openValue":1,"missionType":2,"requestType":-1,"requestCode":-1,"requestValue":150,"rewardType":1,"rewardCode":-1,"rewardValue":20,"knowledge":10,"rewardGuildCoin":10,"rewardGuildExp":5},{"index":2003,"openType":0,"openCode":-1,"openValue":1,"missionType":2,"requestType":-1,"requestCode":-1,"requestValue":300,"rewardType":1,"rewardCode":-1,"rewardValue":30,"knowledge":15,"rewardGuildCoin":-1,"rewardGuildExp":-1},{"index":2004,"openType":0,"openCode":-1,"openValue":1,"missionType":2,"requestType":-1,"requestCode":-1,"requestValue":1000,"rewardType":1,"rewardCode":-1,"rewardValue":50,"knowledge":20,"rewardGuildCoin":-1,"rewardGuildExp":-1},{"index":2005,"openType":0,"openCode":-1,"openValue":1,"missionType":2,"requestType":-1,"requestCode":-1,"requestValue":2000,"rewardType":1,"rewardCode":-1,"rewardValue":100,"knowledge":30,"rewardGuildCoin":-1,"rewardGuildExp":-1},{"index":3000,"openType":0,"openCode":-1,"openValue":1,"missionType":3,"requestType":-1,"requestCode":-1,"requestValue":7,"rewardType":1,"rewardCode":-1,"rewardValue":10,"knowledge":10,"rewardGuildCoin":-1,"rewardGuildExp":-1},{"index":3001,"openType":0,"openCode":-1,"openValue":1,"missionType":3,"requestType":-1,"requestCode":-1,"requestValue":20,"rewardType":1,"rewardCode":-1,"rewardValue":50,"knowledge":20,"rewardGuildCoin":-1,"rewardGuildExp":-1},{"index":3002,"openType":0,"openCode":-1,"openValue":1,"missionType":3,"requestType":-1,"requestCode":-1,"requestValue":39,"rewardType":1,"rewardCode":-1,"rewardValue":100,"knowledge":30,"rewardGuildCoin":-1,"rewardGuildExp":-1},{"index":4000,"openType":0,"openCode":-1,"openValue":1,"missionType":4,"requestType":-1,"requestCode":-1,"requestValue":20,"rewardType":1,"rewardCode":-1,"rewardValue":5,"knowledge":3,"rewardGuildCoin":-1,"rewardGuildExp":-1},{"index":4001,"openType":0,"openCode":-1,"openValue":1,"missionType":4,"requestType":-1,"requestCode":-1,"requestValue":300,"rewardType":1,"rewardCode":-1,"rewardValue":10,"knowledge":5,"rewardGuildCoin":-1,"rewardGuildExp":-1},{"index":4002,"openType":0,"openCode":-1,"openValue":1,"missionType":4,"requestType":-1,"requestCode":-1,"requestValue":1000,"rewardType":1,"rewardCode":-1,"rewardValue":20,"knowledge":10,"rewardGuildCoin":-1,"rewardGuildExp":-1},{"index":4003,"openType":0,"openCode":-1,"openValue":1,"missionType":4,"requestType":-1,"requestCode":-1,"requestValue":3000,"rewardType":1,"rewardCode":-1,"rewardValue":30,"knowledge":15,"rewardGuildCoin":-1,"rewardGuildExp":-1},{"index":4004,"openType":0,"openCode":-1,"openValue":1,"missionType":4,"requestType":-1,"requestCode":-1,"requestValue":5000,"rewardType":1,"rewardCode":-1,"rewardValue":50,"knowledge":20,"rewardGuildCoin":-1,"rewardGuildExp":-1},{"index":4005,"openType":0,"openCode":-1,"openValue":1,"missionType":4,"requestType":-1,"requestCode":-1,"requestValue":10000,"rewardType":1,"rewardCode":-1,"rewardValue":100,"knowledge":30,"rewardGuildCoin":-1,"rewardGuildExp":-1},{"index":5000,"openType":0,"openCode":-1,"openValue":1,"missionType":5,"requestType":-1,"requestCode":-1,"requestValue":10,"rewardType":1,"rewardCode":-1,"rewardValue":10,"knowledge":10,"rewardGuildCoin":-1,"rewardGuildExp":-1},{"index":5001,"openType":0,"openCode":-1,"openValue":1,"missionType":5,"requestType":-1,"requestCode":-1,"requestValue":15,"rewardType":1,"rewardCode":-1,"rewardValue":20,"knowledge":20,"rewardGuildCoin":-1,"rewardGuildExp":-1},{"index":5002,"openType":0,"openCode":-1,"openValue":1,"missionType":5,"requestType":-1,"requestCode":-1,"requestValue":20,"rewardType":1,"rewardCode":-1,"rewardValue":30,"knowledge":30,"rewardGuildCoin":-1,"rewardGuildExp":-1},{"index":5003,"openType":0,"openCode":-1,"openValue":1,"missionType":5,"requestType":-1,"requestCode":-1,"requestValue":30,"rewardType":1,"rewardCode":-1,"rewardValue":50,"knowledge":40,"rewardGuildCoin":-1,"rewardGuildExp":-1},{"index":5004,"openType":0,"openCode":-1,"openValue":1,"missionType":5,"requestType":-1,"requestCode":-1,"requestValue":40,"rewardType":1,"rewardCode":-1,"rewardValue":100,"knowledge":50,"rewardGuildCoin":-1,"rewardGuildExp":-1},{"index":6000,"openType":0,"openCode":-1,"openValue":1,"missionType":8,"requestType":15,"requestCode":-1,"requestValue":500,"rewardType":1,"rewardCode":-1,"rewardValue":10,"knowledge":3,"rewardGuildCoin":-1,"rewardGuildExp":-1},{"index":6001,"openType":0,"openCode":-1,"openValue":1,"missionType":8,"requestType":15,"requestCode":-1,"requestValue":1000,"rewardType":1,"rewardCode":-1,"rewardValue":20,"knowledge":5,"rewardGuildCoin":-1,"rewardGuildExp":-1},{"index":6002,"openType":0,"openCode":-1,"openValue":1,"missionType":8,"requestType":15,"requestCode":-1,"requestValue":5000,"rewardType":1,"rewardCode":-1,"rewardValue":30,"knowledge":10,"rewardGuildCoin":-1,"rewardGuildExp":-1},{"index":6003,"openType":0,"openCode":-1,"openValue":1,"missionType":8,"requestType":15,"requestCode":-1,"requestValue":10000,"rewardType":1,"rewardCode":-1,"rewardValue":50,"knowledge":15,"rewardGuildCoin":-1,"rewardGuildExp":-1},{"index":6004,"openType":0,"openCode":-1,"openValue":1,"missionType":8,"requestType":15,"requestCode":-1,"requestValue":100000,"rewardType":1,"rewardCode":-1,"rewardValue":100,"knowledge":20,"rewardGuildCoin":-1,"rewardGuildExp":-1},{"index":6005,"openType":0,"openCode":-1,"openValue":1,"missionType":8,"requestType":15,"requestCode":-1,"requestValue":1000000,"rewardType":1,"rewardCode":-1,"rewardValue":200,"knowledge":30,"rewardGuildCoin":-1,"rewardGuildExp":-1},{"index":7000,"openType":0,"openCode":-1,"openValue":1,"missionType":11,"requestType":-1,"requestCode":-1,"requestValue":10,"rewardType":1,"rewardCode":-1,"rewardValue":5,"knowledge":3,"rewardGuildCoin":-1,"rewardGuildExp":-1},{"index":7001,"openType":0,"openCode":-1,"openValue":1,"missionType":11,"requestType":-1,"requestCode":-1,"requestValue":50,"rewardType":1,"rewardCode":-1,"rewardValue":10,"knowledge":5,"rewardGuildCoin":-1,"rewardGuildExp":-1},{"index":7002,"openType":0,"openCode":-1,"openValue":1,"missionType":11,"requestType":-1,"requestCode":-1,"requestValue":100,"rewardType":1,"rewardCode":-1,"rewardValue":20,"knowledge":10,"rewardGuildCoin":-1,"rewardGuildExp":-1},{"index":7003,"openType":0,"openCode":-1,"openValue":1,"missionType":11,"requestType":-1,"requestCode":-1,"requestValue":300,"rewardType":1,"rewardCode":-1,"rewardValue":30,"knowledge":15,"rewardGuildCoin":-1,"rewardGuildExp":-1},{"index":7004,"openType":0,"openCode":-1,"openValue":1,"missionType":11,"requestType":-1,"requestCode":-1,"requestValue":500,"rewardType":1,"rewardCode":-1,"rewardValue":50,"knowledge":20,"rewardGuildCoin":-1,"rewardGuildExp":-1},{"index":7005,"openType":0,"openCode":-1,"openValue":1,"missionType":11,"requestType":-1,"requestCode":-1,"requestValue":1000,"rewardType":1,"rewardCode":-1,"rewardValue":100,"knowledge":30,"rewardGuildCoin":-1,"rewardGuildExp":-1},{"index":8000,"openType":0,"openCode":-1,"openValue":1,"missionType":15,"requestType":-1,"requestCode":-1,"requestValue":10,"rewardType":12,"rewardCode":-1,"rewardValue":30,"knowledge":3,"rewardGuildCoin":-1,"rewardGuildExp":-1},{"index":8001,"openType":0,"openCode":-1,"openValue":1,"missionType":15,"requestType":-1,"requestCode":-1,"requestValue":50,"rewardType":12,"rewardCode":-1,"rewardValue":150,"knowledge":5,"rewardGuildCoin":-1,"rewardGuildExp":-1},{"index":8002,"openType":0,"openCode":-1,"openValue":1,"missionType":15,"requestType":-1,"requestCode":-1,"requestValue":100,"rewardType":12,"rewardCode":-1,"rewardValue":300,"knowledge":10,"rewardGuildCoin":-1,"rewardGuildExp":-1},{"index":8003,"openType":0,"openCode":-1,"openValue":1,"missionType":15,"requestType":-1,"requestCode":-1,"requestValue":500,"rewardType":12,"rewardCode":-1,"rewardValue":1000,"knowledge":15,"rewardGuildCoin":-1,"rewardGuildExp":-1},{"index":8004,"openType":0,"openCode":-1,"openValue":1,"missionType":15,"requestType":-1,"requestCode":-1,"requestValue":1000,"rewardType":12,"rewardCode":-1,"rewardValue":2000,"knowledge":20,"rewardGuildCoin":-1,"rewardGuildExp":-1},{"index":8005,"openType":0,"openCode":-1,"openValue":1,"missionType":15,"requestType":-1,"requestCode":-1,"requestValue":3000,"rewardType":12,"rewardCode":-1,"rewardValue":5000,"knowledge":30,"rewardGuildCoin":-1,"rewardGuildExp":-1},{"index":9000,"openType":0,"openCode":-1,"openValue":1,"missionType":16,"requestType":15,"requestCode":-1,"requestValue":100,"rewardType":1,"rewardCode":-1,"rewardValue":10,"knowledge":3,"rewardGuildCoin":-1,"rewardGuildExp":-1},{"index":9001,"openType":0,"openCode":-1,"openValue":1,"missionType":16,"requestType":15,"requestCode":-1,"requestValue":500,"rewardType":1,"rewardCode":-1,"rewardValue":20,"knowledge":5,"rewardGuildCoin":-1,"rewardGuildExp":-1},{"index":9002,"openType":0,"openCode":-1,"openValue":1,"missionType":16,"requestType":15,"requestCode":-1,"requestValue":1000,"rewardType":1,"rewardCode":-1,"rewardValue":30,"knowledge":10,"rewardGuildCoin":-1,"rewardGuildExp":-1},{"index":9003,"openType":0,"openCode":-1,"openValue":1,"missionType":16,"requestType":15,"requestCode":-1,"requestValue":5000,"rewardType":1,"rewardCode":-1,"rewardValue":50,"knowledge":15,"rewardGuildCoin":-1,"rewardGuildExp":-1},{"index":9004,"openType":0,"openCode":-1,"openValue":1,"missionType":16,"requestType":15,"requestCode":-1,"requestValue":10000,"rewardType":1,"rewardCode":-1,"rewardValue":100,"knowledge":20,"rewardGuildCoin":-1,"rewardGuildExp":-1},{"index":9005,"openType":0,"openCode":-1,"openValue":1,"missionType":16,"requestType":15,"requestCode":-1,"requestValue":50000,"rewardType":1,"rewardCode":-1,"rewardValue":150,"knowledge":30,"rewardGuildCoin":-1,"rewardGuildExp":-1},{"index":10000,"openType":0,"openCode":-1,"openValue":1,"missionType":18,"requestType":-1,"requestCode":-1,"requestValue":30,"rewardType":1,"rewardCode":-1,"rewardValue":10,"knowledge":3,"rewardGuildCoin":-1,"rewardGuildExp":-1},{"index":10001,"openType":0,"openCode":-1,"openValue":1,"missionType":18,"requestType":-1,"requestCode":-1,"requestValue":100,"rewardType":1,"rewardCode":-1,"rewardValue":20,"knowledge":5,"rewardGuildCoin":-1,"rewardGuildExp":-1},{"index":10002,"openType":0,"openCode":-1,"openValue":1,"missionType":18,"requestType":-1,"requestCode":-1,"requestValue":500,"rewardType":1,"rewardCode":-1,"rewardValue":30,"knowledge":10,"rewardGuildCoin":-1,"rewardGuildExp":-1},{"index":10003,"openType":0,"openCode":-1,"openValue":1,"missionType":18,"requestType":-1,"requestCode":-1,"requestValue":1000,"rewardType":1,"rewardCode":-1,"rewardValue":50,"knowledge":15,"rewardGuildCoin":-1,"rewardGuildExp":-1},{"index":10004,"openType":0,"openCode":-1,"openValue":1,"missionType":18,"requestType":-1,"requestCode":-1,"requestValue":5000,"rewardType":1,"rewardCode":-1,"rewardValue":100,"knowledge":20,"rewardGuildCoin":-1,"rewardGuildExp":-1},{"index":10005,"openType":0,"openCode":-1,"openValue":1,"missionType":18,"requestType":-1,"requestCode":-1,"requestValue":10000,"rewardType":1,"rewardCode":-1,"rewardValue":150,"knowledge":30,"rewardGuildCoin":-1,"rewardGuildExp":-1},{"index":11000,"openType":0,"openCode":-1,"openValue":1,"missionType":20,"requestType":-1,"requestCode":-1,"requestValue":30,"rewardType":1,"rewardCode":-1,"rewardValue":10,"knowledge":3,"rewardGuildCoin":-1,"rewardGuildExp":-1},{"index":11001,"openType":0,"openCode":-1,"openValue":1,"missionType":20,"requestType":-1,"requestCode":-1,"requestValue":100,"rewardType":1,"rewardCode":-1,"rewardValue":20,"knowledge":5,"rewardGuildCoin":-1,"rewardGuildExp":-1},{"index":11002,"openType":0,"openCode":-1,"openValue":1,"missionType":20,"requestType":-1,"requestCode":-1,"requestValue":500,"rewardType":1,"rewardCode":-1,"rewardValue":30,"knowledge":10,"rewardGuildCoin":-1,"rewardGuildExp":-1},{"index":11003,"openType":0,"openCode":-1,"openValue":1,"missionType":20,"requestType":-1,"requestCode":-1,"requestValue":1000,"rewardType":1,"rewardCode":-1,"rewardValue":50,"knowledge":15,"rewardGuildCoin":-1,"rewardGuildExp":-1},{"index":11004,"openType":0,"openCode":-1,"openValue":1,"missionType":20,"requestType":-1,"requestCode":-1,"requestValue":5000,"rewardType":1,"rewardCode":-1,"rewardValue":100,"knowledge":20,"rewardGuildCoin":-1,"rewardGuildExp":-1},{"index":11005,"openType":0,"openCode":-1,"openValue":1,"missionType":20,"requestType":-1,"requestCode":-1,"requestValue":10000,"rewardType":1,"rewardCode":-1,"rewardValue":150,"knowledge":30,"rewardGuildCoin":-1,"rewardGuildExp":-1},{"index":12000,"openType":0,"openCode":-1,"openValue":1,"missionType":25,"requestType":-1,"requestCode":-1,"requestValue":5,"rewardType":1,"rewardCode":-1,"rewardValue":5,"knowledge":3,"rewardGuildCoin":-1,"rewardGuildExp":-1},{"index":12001,"openType":0,"openCode":-1,"openValue":1,"missionType":25,"requestType":-1,"requestCode":-1,"requestValue":50,"rewardType":1,"rewardCode":-1,"rewardValue":10,"knowledge":5,"rewardGuildCoin":-1,"rewardGuildExp":-1},{"index":12002,"openType":0,"openCode":-1,"openValue":1,"missionType":25,"requestType":-1,"requestCode":-1,"requestValue":250,"rewardType":1,"rewardCode":-1,"rewardValue":20,"knowledge":10,"rewardGuildCoin":-1,"rewardGuildExp":-1},{"index":12003,"openType":0,"openCode":-1,"openValue":1,"missionType":25,"requestType":-1,"requestCode":-1,"requestValue":500,"rewardType":1,"rewardCode":-1,"rewardValue":30,"knowledge":15,"rewardGuildCoin":-1,"rewardGuildExp":-1},{"index":12004,"openType":0,"openCode":-1,"openValue":1,"missionType":25,"requestType":-1,"requestCode":-1,"requestValue":2500,"rewardType":1,"rewardCode":-1,"rewardValue":50,"knowledge":20,"rewardGuildCoin":-1,"rewardGuildExp":-1},{"index":12005,"openType":0,"openCode":-1,"openValue":1,"missionType":25,"requestType":-1,"requestCode":-1,"requestValue":5000,"rewardType":1,"rewardCode":-1,"rewardValue":100,"knowledge":30,"rewardGuildCoin":-1,"rewardGuildExp":-1},{"index":13000,"openType":0,"openCode":-1,"openValue":1,"missionType":27,"requestType":-1,"requestCode":-1,"requestValue":10,"rewardType":1,"rewardCode":-1,"rewardValue":5,"knowledge":3,"rewardGuildCoin":-1,"rewardGuildExp":-1},{"index":13001,"openType":0,"openCode":-1,"openValue":1,"missionType":27,"requestType":-1,"requestCode":-1,"requestValue":50,"rewardType":1,"rewardCode":-1,"rewardValue":10,"knowledge":5,"rewardGuildCoin":-1,"rewardGuildExp":-1},{"index":13002,"openType":0,"openCode":-1,"openValue":1,"missionType":27,"requestType":-1,"requestCode":-1,"requestValue":250,"rewardType":1,"rewardCode":-1,"rewardValue":20,"knowledge":10,"rewardGuildCoin":-1,"rewardGuildExp":-1},{"index":13003,"openType":0,"openCode":-1,"openValue":1,"missionType":27,"requestType":-1,"requestCode":-1,"requestValue":500,"rewardType":1,"rewardCode":-1,"rewardValue":30,"knowledge":15,"rewardGuildCoin":-1,"rewardGuildExp":-1},{"index":13004,"openType":0,"openCode":-1,"openValue":1,"missionType":27,"requestType":-1,"requestCode":-1,"requestValue":1000,"rewardType":1,"rewardCode":-1,"rewardValue":50,"knowledge":20,"rewardGuildCoin":-1,"rewardGuildExp":-1},{"index":13005,"openType":0,"openCode":-1,"openValue":1,"missionType":27,"requestType":-1,"requestCode":-1,"requestValue":1500,"rewardType":1,"rewardCode":-1,"rewardValue":100,"knowledge":30,"rewardGuildCoin":-1,"rewardGuildExp":-1},{"index":14000,"openType":0,"openCode":-1,"openValue":1,"missionType":39,"requestType":-1,"requestCode":-1,"requestValue":3,"rewardType":25,"rewardCode":-1,"rewardValue":1,"knowledge":3,"rewardGuildCoin":-1,"rewardGuildExp":-1},{"index":14001,"openType":0,"openCode":-1,"openValue":1,"missionType":39,"requestType":-1,"requestCode":-1,"requestValue":24,"rewardType":25,"rewardCode":-1,"rewardValue":2,"knowledge":5,"rewardGuildCoin":-1,"rewardGuildExp":-1},{"index":14002,"openType":0,"openCode":-1,"openValue":1,"missionType":39,"requestType":-1,"requestCode":-1,"requestValue":45,"rewardType":25,"rewardCode":-1,"rewardValue":3,"knowledge":10,"rewardGuildCoin":-1,"rewardGuildExp":-1},{"index":14003,"openType":0,"openCode":-1,"openValue":1,"missionType":39,"requestType":-1,"requestCode":-1,"requestValue":69,"rewardType":25,"rewardCode":-1,"rewardValue":5,"knowledge":15,"rewardGuildCoin":-1,"rewardGuildExp":-1},{"index":14004,"openType":0,"openCode":-1,"openValue":1,"missionType":39,"requestType":-1,"requestCode":-1,"requestValue":90,"rewardType":25,"rewardCode":-1,"rewardValue":5,"knowledge":20,"rewardGuildCoin":-1,"rewardGuildExp":-1},{"index":14005,"openType":0,"openCode":-1,"openValue":1,"missionType":39,"requestType":-1,"requestCode":-1,"requestValue":135,"rewardType":25,"rewardCode":-1,"rewardValue":5,"knowledge":30,"rewardGuildCoin":-1,"rewardGuildExp":-1},{"index":15000,"openType":0,"openCode":-1,"openValue":1,"missionType":45,"requestType":0,"requestCode":-1,"requestValue":10000,"rewardType":1,"rewardCode":-1,"rewardValue":10,"knowledge":3,"rewardGuildCoin":-1,"rewardGuildExp":-1},{"index":15001,"openType":0,"openCode":-1,"openValue":1,"missionType":45,"requestType":0,"requestCode":-1,"requestValue":100000,"rewardType":1,"rewardCode":-1,"rewardValue":20,"knowledge":5,"rewardGuildCoin":-1,"rewardGuildExp":-1},{"index":15002,"openType":0,"openCode":-1,"openValue":1,"missionType":45,"requestType":0,"requestCode":-1,"requestValue":1000000,"rewardType":1,"rewardCode":-1,"rewardValue":30,"knowledge":10,"rewardGuildCoin":-1,"rewardGuildExp":-1},{"index":15003,"openType":0,"openCode":-1,"openValue":1,"missionType":45,"requestType":0,"requestCode":-1,"requestValue":5000000,"rewardType":1,"rewardCode":-1,"rewardValue":50,"knowledge":15,"rewardGuildCoin":-1,"rewardGuildExp":-1},{"index":15004,"openType":0,"openCode":-1,"openValue":1,"missionType":45,"requestType":0,"requestCode":-1,"requestValue":10000000,"rewardType":1,"rewardCode":-1,"rewardValue":100,"knowledge":20,"rewardGuildCoin":-1,"rewardGuildExp":-1},{"index":15005,"openType":0,"openCode":-1,"openValue":1,"missionType":45,"requestType":0,"requestCode":-1,"requestValue":50000000,"rewardType":1,"rewardCode":-1,"rewardValue":150,"knowledge":30,"rewardGuildCoin":-1,"rewardGuildExp":-1},{"index":15006,"openType":0,"openCode":-1,"openValue":1,"missionType":45,"requestType":0,"requestCode":-1,"requestValue":1000000000,"rewardType":1,"rewardCode":-1,"rewardValue":300,"knowledge":50,"rewardGuildCoin":-1,"rewardGuildExp":-1},{"index":16000,"openType":0,"openCode":-1,"openValue":1,"missionType":96,"requestType":0,"requestCode":-1,"requestValue":10000,"rewardType":1,"rewardCode":-1,"rewardValue":10,"knowledge":3,"rewardGuildCoin":-1,"rewardGuildExp":-1},{"index":16001,"openType":0,"openCode":-1,"openValue":1,"missionType":96,"requestType":0,"requestCode":-1,"requestValue":100000,"rewardType":1,"rewardCode":-1,"rewardValue":20,"knowledge":5,"rewardGuildCoin":-1,"rewardGuildExp":-1},{"index":16002,"openType":0,"openCode":-1,"openValue":1,"missionType":96,"requestType":0,"requestCode":-1,"requestValue":1000000,"rewardType":1,"rewardCode":-1,"rewardValue":30,"knowledge":10,"rewardGuildCoin":-1,"rewardGuildExp":-1},{"index":16003,"openType":0,"openCode":-1,"openValue":1,"missionType":96,"requestType":0,"requestCode":-1,"requestValue":5000000,"rewardType":1,"rewardCode":-1,"rewardValue":50,"knowledge":15,"rewardGuildCoin":-1,"rewardGuildExp":-1},{"index":16004,"openType":0,"openCode":-1,"openValue":1,"missionType":96,"requestType":0,"requestCode":-1,"requestValue":10000000,"rewardType":1,"rewardCode":-1,"rewardValue":100,"knowledge":20,"rewardGuildCoin":-1,"rewardGuildExp":-1},{"index":16005,"openType":0,"openCode":-1,"openValue":1,"missionType":96,"requestType":0,"requestCode":-1,"requestValue":1000000000,"rewardType":1,"rewardCode":-1,"rewardValue":150,"knowledge":30,"rewardGuildCoin":-1,"rewardGuildExp":-1},{"index":17000,"openType":0,"openCode":-1,"openValue":1,"missionType":58,"requestType":-1,"requestCode":-1,"requestValue":30,"rewardType":1,"rewardCode":-1,"rewardValue":50,"knowledge":3,"rewardGuildCoin":-1,"rewardGuildExp":-1},{"index":17001,"openType":0,"openCode":-1,"openValue":1,"missionType":58,"requestType":-1,"requestCode":-1,"requestValue":100,"rewardType":1,"rewardCode":-1,"rewardValue":100,"knowledge":5,"rewardGuildCoin":-1,"rewardGuildExp":-1},{"index":17002,"openType":0,"openCode":-1,"openValue":1,"missionType":58,"requestType":-1,"requestCode":-1,"requestValue":250,"rewardType":1,"rewardCode":-1,"rewardValue":200,"knowledge":10,"rewardGuildCoin":-1,"rewardGuildExp":-1},{"index":17003,"openType":0,"openCode":-1,"openValue":1,"missionType":58,"requestType":-1,"requestCode":-1,"requestValue":500,"rewardType":1,"rewardCode":-1,"rewardValue":300,"knowledge":15,"rewardGuildCoin":-1,"rewardGuildExp":-1},{"index":17004,"openType":0,"openCode":-1,"openValue":1,"missionType":58,"requestType":-1,"requestCode":-1,"requestValue":1000,"rewardType":1,"rewardCode":-1,"rewardValue":500,"knowledge":20,"rewardGuildCoin":-1,"rewardGuildExp":-1},{"index":17005,"openType":0,"openCode":-1,"openValue":1,"missionType":58,"requestType":-1,"requestCode":-1,"requestValue":2000,"rewardType":1,"rewardCode":-1,"rewardValue":750,"knowledge":30,"rewardGuildCoin":-1,"rewardGuildExp":-1},{"index":18000,"openType":0,"openCode":-1,"openValue":1,"missionType":59,"requestType":-1,"requestCode":-1,"requestValue":1,"rewardType":1,"rewardCode":-1,"rewardValue":50,"knowledge":3,"rewardGuildCoin":-1,"rewardGuildExp":-1},{"index":18001,"openType":0,"openCode":-1,"openValue":1,"missionType":59,"requestType":-1,"requestCode":-1,"requestValue":3,"rewardType":1,"rewardCode":-1,"rewardValue":100,"knowledge":5,"rewardGuildCoin":-1,"rewardGuildExp":-1},{"index":18002,"openType":0,"openCode":-1,"openValue":1,"missionType":59,"requestType":-1,"requestCode":-1,"requestValue":5,"rewardType":1,"rewardCode":-1,"rewardValue":200,"knowledge":10,"rewardGuildCoin":-1,"rewardGuildExp":-1},{"index":18003,"openType":0,"openCode":-1,"openValue":1,"missionType":59,"requestType":-1,"requestCode":-1,"requestValue":10,"rewardType":1,"rewardCode":-1,"rewardValue":300,"knowledge":15,"rewardGuildCoin":-1,"rewardGuildExp":-1},{"index":18004,"openType":0,"openCode":-1,"openValue":1,"missionType":59,"requestType":-1,"requestCode":-1,"requestValue":20,"rewardType":1,"rewardCode":-1,"rewardValue":500,"knowledge":20,"rewardGuildCoin":-1,"rewardGuildExp":-1},{"index":18005,"openType":0,"openCode":-1,"openValue":1,"missionType":59,"requestType":-1,"requestCode":-1,"requestValue":40,"rewardType":1,"rewardCode":-1,"rewardValue":750,"knowledge":30,"rewardGuildCoin":-1,"rewardGuildExp":-1},{"index":19000,"openType":0,"openCode":-1,"openValue":1,"missionType":60,"requestType":-1,"requestCode":-1,"requestValue":7,"rewardType":1,"rewardCode":-1,"rewardValue":100,"knowledge":3,"rewardGuildCoin":-1,"rewardGuildExp":-1},{"index":19001,"openType":0,"openCode":-1,"openValue":1,"missionType":60,"requestType":-1,"requestCode":-1,"requestValue":30,"rewardType":1,"rewardCode":-1,"rewardValue":200,"knowledge":5,"rewardGuildCoin":-1,"rewardGuildExp":-1},{"index":19002,"openType":0,"openCode":-1,"openValue":1,"missionType":60,"requestType":-1,"requestCode":-1,"requestValue":60,"rewardType":1,"rewardCode":-1,"rewardValue":300,"knowledge":10,"rewardGuildCoin":-1,"rewardGuildExp":-1},{"index":19003,"openType":0,"openCode":-1,"openValue":1,"missionType":60,"requestType":-1,"requestCode":-1,"requestValue":90,"rewardType":1,"rewardCode":-1,"rewardValue":500,"knowledge":15,"rewardGuildCoin":-1,"rewardGuildExp":-1},{"index":19004,"openType":0,"openCode":-1,"openValue":1,"missionType":60,"requestType":-1,"requestCode":-1,"requestValue":180,"rewardType":1,"rewardCode":-1,"rewardValue":750,"knowledge":20,"rewardGuildCoin":-1,"rewardGuildExp":-1},{"index":19005,"openType":0,"openCode":-1,"openValue":1,"missionType":60,"requestType":-1,"requestCode":-1,"requestValue":365,"rewardType":1,"rewardCode":-1,"rewardValue":1000,"knowledge":30,"rewardGuildCoin":-1,"rewardGuildExp":-1}]}